richernural/__init__.py
richernural/nural.py
richernural-0.2.dist-info/METADATA
richernural-0.2.dist-info/WHEEL
richernural-0.2.dist-info/top_level.txt
richernural-0.2.dist-info/RECORD
